{
  "baselineUnit": "0.5rem",
  "fontFiles": [
    {
      "family": "sans",
      "path": "../fonts/UbuntuSans-Regular.woff"
    }
  ],
  "elements": {
    "h1": {
      "fontSize": "2.25rem",
      "lineHeight": "3rem",
      "fontFamily": "sans",
      "fontWeight": 500,
      "fontStyle": "normal",
      "spaceAfter": "1rem",
      "nudgeTop": "0.20028rem"
    },
    "h2": {
      "fontSize": "2.25rem",
      "lineHeight": "2.5rem",
      "fontFamily": "sans",
      "fontWeight": 400,
      "fontStyle": "normal",
      "spaceAfter": "1rem",
      "nudgeTop": "0.45028rem"
    },
    "h3": {
      "fontSize": "1.5rem",
      "lineHeight": "2rem",
      "fontFamily": "sans",
      "fontWeight": 500,
      "fontStyle": "normal",
      "spaceAfter": "0.5rem",
      "nudgeTop": "0.46917rem"
    },
    "h4": {
      "fontSize": "1.5rem",
      "lineHeight": "2rem",
      "fontFamily": "sans",
      "fontWeight": 400,
      "fontStyle": "normal",
      "spaceAfter": "0.5rem",
      "nudgeTop": "0.46917rem"
    },
    "h5": {
      "fontSize": "1rem",
      "lineHeight": "1.5rem",
      "fontFamily": "sans",
      "fontWeight": 500,
      "fontStyle": "normal",
      "spaceAfter": "1rem",
      "nudgeTop": "0.41rem"
    },
    "h6": {
      "fontSize": "1rem",
      "lineHeight": "1.5rem",
      "fontFamily": "sans",
      "fontWeight": 400,
      "fontStyle": "normal",
      "spaceAfter": "1rem",
      "nudgeTop": "0.41rem"
    },
    "p": {
      "fontSize": "1rem",
      "lineHeight": "1.5rem",
      "fontFamily": "sans",
      "fontWeight": 400,
      "fontStyle": "normal",
      "spaceAfter": "1rem",
      "nudgeTop": "0.41rem"
    }
  }
}